Metadata-Version: 2.1
Name: waybacktools
Version: 0.1.2
Summary: Unofficial API Wrapper for the Wayback Machine
Home-page: https://github.com/radian462/waybacktools
Download-URL: https://github.com/radian462/waybacktools
Author: radian462
Author-email: no-number-email@proton.me
Maintainer: radian462
Maintainer-email: no-number-email@proton.me
License: MIT License
Keywords: waybacktools,wayback,waybackmachine
Classifier: License :: OSI Approved :: MIT License
Classifier: Programming Language :: Python :: 3.8
Classifier: Programming Language :: Python :: 3.9
Classifier: Programming Language :: Python :: 3.10
Classifier: Programming Language :: Python :: 3.11
Classifier: Programming Language :: Python :: 3.12
Classifier: Programming Language :: Python :: 3 :: Only
Requires-Python: >=3.8
License-File: LICENSE
Requires-Dist: beautifulsoup4
Requires-Dist: playwright
Requires-Dist: requests
